{"mobilenet_tinyimagenet_025_layer27": {"Workload": "mobilenet_tinyimagenet_025_layer27", "Optimized_metric_1": "energy", "Optimized_metric_2": "delay", "pJ/Compute": "4.12524", "Utilization": "0.285714", "Cycles": "49152", "Energy [uJ]": "9.73266", "EDP [J*cycle]": "4.783797e-01", "Area [mm^2]": "1.928614", "LastLevelAccesses": "17408", "MAC energy [pJ]": "2.200350", "Computes": "2359296", "Algorithmic computes": "2359296", "Runtime [s]": "24.37"}, "mobilenet_tinyimagenet_025_layer1": {"Workload": "mobilenet_tinyimagenet_025_layer1", "Optimized_metric_1": "energy", "Optimized_metric_2": "delay", "pJ/Compute": "10.6097", "Utilization": "0.75", "Cycles": "21504", "Energy [uJ]": "28.7471", "EDP [J*cycle]": "6.181777e-01", "Area [mm^2]": "1.928614", "LastLevelAccesses": "126168", "MAC energy [pJ]": "2.200350", "Computes": "2709504", "Algorithmic computes": "2709504", "Runtime [s]": "7.15"}, "mobilenet_tinyimagenet_025_layer18": {"Workload": "mobilenet_tinyimagenet_025_layer18", "Optimized_metric_1": "energy", "Optimized_metric_2": "delay", "pJ/Compute": "3.12807", "Utilization": "0.928571", "Cycles": "159744", "Energy [uJ]": "77.9517", "EDP [J*cycle]": "1.245231e+01", "Area [mm^2]": "1.928614", "LastLevelAccesses": "43648", "MAC energy [pJ]": "2.200350", "Computes": "24920064", "Algorithmic computes": "24920064", "Runtime [s]": "26.17"}, "mobilenet_tinyimagenet_025_layer17": {"Workload": "mobilenet_tinyimagenet_025_layer17", "Optimized_metric_1": "energy", "Optimized_metric_2": "delay", "pJ/Compute": "4.08199", "Utilization": "0.190476", "Cycles": "86528", "Energy [uJ]": "11.3026", "EDP [J*cycle]": "9.779914e-01", "Area [mm^2]": "1.928614", "LastLevelAccesses": "23680", "MAC energy [pJ]": "2.200350", "Computes": "2768896", "Algorithmic computes": "2768896", "Runtime [s]": "18.16"}, "mobilenet_tinyimagenet_025_layer5": {"Workload": "mobilenet_tinyimagenet_025_layer5", "Optimized_metric_1": "energy", "Optimized_metric_2": "delay", "pJ/Compute": "10.3364", "Utilization": "0.52381", "Cycles": "17600", "Energy [uJ]": "16.009", "EDP [J*cycle]": "2.817579e-01", "Area [mm^2]": "1.928614", "LastLevelAccesses": "72664", "MAC energy [pJ]": "2.200350", "Computes": "1548800", "Algorithmic computes": "1548800", "Runtime [s]": "14.37"}, "mobilenet_tinyimagenet_025_layer19": {"Workload": "mobilenet_tinyimagenet_025_layer19", "Optimized_metric_1": "energy", "Optimized_metric_2": "delay", "pJ/Compute": "4.08199", "Utilization": "0.190476", "Cycles": "86528", "Energy [uJ]": "11.3026", "EDP [J*cycle]": "9.779914e-01", "Area [mm^2]": "1.928614", "LastLevelAccesses": "23680", "MAC energy [pJ]": "2.200350", "Computes": "2768896", "Algorithmic computes": "2768896", "Runtime [s]": "18.16"}, "mobilenet_tinyimagenet_025_layer8": {"Workload": "mobilenet_tinyimagenet_025_layer8", "Optimized_metric_1": "energy", "Optimized_metric_2": "delay", "pJ/Compute": "4.25059", "Utilization": "0.428571", "Cycles": "93312", "Energy [uJ]": "28.5574", "EDP [J*cycle]": "2.664751e+00", "Area [mm^2]": "1.928614", "LastLevelAccesses": "61216", "MAC energy [pJ]": "2.200350", "Computes": "6718464", "Algorithmic computes": "6718464", "Runtime [s]": "28.79"}, "mobilenet_tinyimagenet_025_layer15": {"Workload": "mobilenet_tinyimagenet_025_layer15", "Optimized_metric_1": "energy", "Optimized_metric_2": "delay", "pJ/Compute": "4.08199", "Utilization": "0.190476", "Cycles": "86528", "Energy [uJ]": "11.3026", "EDP [J*cycle]": "9.779914e-01", "Area [mm^2]": "1.928614", "LastLevelAccesses": "23680", "MAC energy [pJ]": "2.200350", "Computes": "2768896", "Algorithmic computes": "2768896", "Runtime [s]": "18.46"}, "mobilenet_tinyimagenet_025_layer11": {"Workload": "mobilenet_tinyimagenet_025_layer11", "Optimized_metric_1": "energy", "Optimized_metric_2": "delay", "pJ/Compute": "5.28045", "Utilization": "0.571429", "Cycles": "31104", "Energy [uJ]": "15.7673", "EDP [J*cycle]": "4.904276e-01", "Area [mm^2]": "1.928614", "LastLevelAccesses": "47168", "MAC energy [pJ]": "2.200350", "Computes": "2985984", "Algorithmic computes": "2985984", "Runtime [s]": "21.53"}, "mobilenet_tinyimagenet_025_layer7": {"Workload": "mobilenet_tinyimagenet_025_layer7", "Optimized_metric_1": "energy", "Optimized_metric_2": "delay", "pJ/Compute": "7.79896", "Utilization": "0.47619", "Cycles": "38720", "Energy [uJ]": "24.1581", "EDP [J*cycle]": "9.354002e-01", "Area [mm^2]": "1.928614", "LastLevelAccesses": "96928", "MAC energy [pJ]": "2.200350", "Computes": "3097600", "Algorithmic computes": "3097600", "Runtime [s]": "20.84"}, "mobilenet_tinyimagenet_025_layer4": {"Workload": "mobilenet_tinyimagenet_025_layer4", "Optimized_metric_1": "energy", "Optimized_metric_2": "delay", "pJ/Compute": "5.69997", "Utilization": "0.785714", "Cycles": "52800", "Energy [uJ]": "39.7265", "EDP [J*cycle]": "2.097559e+00", "Area [mm^2]": "1.928614", "LastLevelAccesses": "123056", "MAC energy [pJ]": "2.200350", "Computes": "6969600", "Algorithmic computes": "6969600", "Runtime [s]": "15.81"}, "mobilenet_tinyimagenet_025_layer22": {"Workload": "mobilenet_tinyimagenet_025_layer22", "Optimized_metric_1": "energy", "Optimized_metric_2": "delay", "pJ/Compute": "3.12807", "Utilization": "0.928571", "Cycles": "159744", "Energy [uJ]": "77.9517", "EDP [J*cycle]": "1.245231e+01", "Area [mm^2]": "1.928614", "LastLevelAccesses": "43648", "MAC energy [pJ]": "2.200350", "Computes": "24920064", "Algorithmic computes": "24920064", "Runtime [s]": "26.30"}, "mobilenet_tinyimagenet_025_layer6": {"Workload": "mobilenet_tinyimagenet_025_layer6", "Optimized_metric_1": "energy", "Optimized_metric_2": "delay", "pJ/Compute": "3.36737", "Utilization": "0.714286", "Cycles": "232320", "Energy [uJ]": "93.877", "EDP [J*cycle]": "2.180951e+01", "Area [mm^2]": "1.928614", "LastLevelAccesses": "101536", "MAC energy [pJ]": "2.200350", "Computes": "27878400", "Algorithmic computes": "27878400", "Runtime [s]": "31.20"}, "mobilenet_tinyimagenet_025_layer24": {"Workload": "mobilenet_tinyimagenet_025_layer24", "Optimized_metric_1": "energy", "Optimized_metric_2": "delay", "pJ/Compute": "3.7965", "Utilization": "0.857143", "Cycles": "36864", "Energy [uJ]": "20.1534", "EDP [J*cycle]": "7.429358e-01", "Area [mm^2]": "1.928614", "LastLevelAccesses": "31552", "MAC energy [pJ]": "2.200350", "Computes": "5308416", "Algorithmic computes": "5308416", "Runtime [s]": "30.83"}, "mobilenet_tinyimagenet_025_layer9": {"Workload": "mobilenet_tinyimagenet_025_layer9", "Optimized_metric_1": "energy", "Optimized_metric_2": "delay", "pJ/Compute": "6.54901", "Utilization": "0.571429", "Cycles": "15552", "Energy [uJ]": "9.77762", "EDP [J*cycle]": "1.520616e-01", "Area [mm^2]": "1.928614", "LastLevelAccesses": "35248", "MAC energy [pJ]": "2.200350", "Computes": "1492992", "Algorithmic computes": "1492992", "Runtime [s]": "19.27"}, "mobilenet_tinyimagenet_025_layer25": {"Workload": "mobilenet_tinyimagenet_025_layer25", "Optimized_metric_1": "energy", "Optimized_metric_2": "delay", "pJ/Compute": "4.23823", "Utilization": "0.571429", "Cycles": "12288", "Energy [uJ]": "4.99962", "EDP [J*cycle]": "6.143536e-02", "Area [mm^2]": "1.928614", "LastLevelAccesses": "11008", "MAC energy [pJ]": "2.200350", "Computes": "1179648", "Algorithmic computes": "1179648", "Runtime [s]": "22.68"}, "mobilenet_tinyimagenet_025_layer20": {"Workload": "mobilenet_tinyimagenet_025_layer20", "Optimized_metric_1": "energy", "Optimized_metric_2": "delay", "pJ/Compute": "3.12807", "Utilization": "0.928571", "Cycles": "159744", "Energy [uJ]": "77.9517", "EDP [J*cycle]": "1.245231e+01", "Area [mm^2]": "1.928614", "LastLevelAccesses": "43648", "MAC energy [pJ]": "2.200350", "Computes": "24920064", "Algorithmic computes": "24920064", "Runtime [s]": "26.54"}, "mobilenet_tinyimagenet_025_layer10": {"Workload": "mobilenet_tinyimagenet_025_layer10", "Optimized_metric_1": "energy", "Optimized_metric_2": "delay", "pJ/Compute": "3.22183", "Utilization": "0.642857", "Cycles": "248832", "Energy [uJ]": "86.5829", "EDP [J*cycle]": "2.154460e+01", "Area [mm^2]": "1.928614", "LastLevelAccesses": "67776", "MAC energy [pJ]": "2.200350", "Computes": "26873856", "Algorithmic computes": "26873856", "Runtime [s]": "30.75"}, "mobilenet_tinyimagenet_025_layer13": {"Workload": "mobilenet_tinyimagenet_025_layer13", "Optimized_metric_1": "energy", "Optimized_metric_2": "delay", "pJ/Compute": "4.71627", "Utilization": "0.190476", "Cycles": "43264", "Energy [uJ]": "6.52943", "EDP [J*cycle]": "2.824892e-01", "Area [mm^2]": "1.928614", "LastLevelAccesses": "17248", "MAC energy [pJ]": "2.200350", "Computes": "1384448", "Algorithmic computes": "1384448", "Runtime [s]": "16.82"}, "mobilenet_tinyimagenet_025_layer14": {"Workload": "mobilenet_tinyimagenet_025_layer14", "Optimized_metric_1": "energy", "Optimized_metric_2": "delay", "pJ/Compute": "3.12807", "Utilization": "0.928571", "Cycles": "159744", "Energy [uJ]": "77.9517", "EDP [J*cycle]": "1.245231e+01", "Area [mm^2]": "1.928614", "LastLevelAccesses": "43648", "MAC energy [pJ]": "2.200350", "Computes": "24920064", "Algorithmic computes": "24920064", "Runtime [s]": "26.78"}, "mobilenet_tinyimagenet_025_layer23": {"Workload": "mobilenet_tinyimagenet_025_layer23", "Optimized_metric_1": "energy", "Optimized_metric_2": "delay", "pJ/Compute": "4.08199", "Utilization": "0.190476", "Cycles": "86528", "Energy [uJ]": "11.3026", "EDP [J*cycle]": "9.779914e-01", "Area [mm^2]": "1.928614", "LastLevelAccesses": "23680", "MAC energy [pJ]": "2.200350", "Computes": "2768896", "Algorithmic computes": "2768896", "Runtime [s]": "18.58"}, "mobilenet_tinyimagenet_025_layer3": {"Workload": "mobilenet_tinyimagenet_025_layer3", "Optimized_metric_1": "energy", "Optimized_metric_2": "delay", "pJ/Compute": "17.9475", "Utilization": "0.609524", "Cycles": "15680", "Energy [uJ]": "28.817", "EDP [J*cycle]": "4.518510e-01", "Area [mm^2]": "1.928614", "LastLevelAccesses": "150544", "MAC energy [pJ]": "2.200350", "Computes": "1605632", "Algorithmic computes": "1605632", "Runtime [s]": "22.56"}, "mobilenet_tinyimagenet_025_layer2": {"Workload": "mobilenet_tinyimagenet_025_layer2", "Optimized_metric_1": "energy", "Optimized_metric_2": "delay", "pJ/Compute": "5.41429", "Utilization": "1", "Cycles": "43008", "Energy [uJ]": "39.1201", "EDP [J*cycle]": "1.682477e+00", "Area [mm^2]": "1.928614", "LastLevelAccesses": "102352", "MAC energy [pJ]": "2.200350", "Computes": "7225344", "Algorithmic computes": "7225344", "Runtime [s]": "11.20"}, "mobilenet_tinyimagenet_025_layer21": {"Workload": "mobilenet_tinyimagenet_025_layer21", "Optimized_metric_1": "energy", "Optimized_metric_2": "delay", "pJ/Compute": "4.08199", "Utilization": "0.190476", "Cycles": "86528", "Energy [uJ]": "11.3026", "EDP [J*cycle]": "9.779914e-01", "Area [mm^2]": "1.928614", "LastLevelAccesses": "23680", "MAC energy [pJ]": "2.200350", "Computes": "2768896", "Algorithmic computes": "2768896", "Runtime [s]": "18.04"}, "mobilenet_tinyimagenet_025_layer16": {"Workload": "mobilenet_tinyimagenet_025_layer16", "Optimized_metric_1": "energy", "Optimized_metric_2": "delay", "pJ/Compute": "3.12807", "Utilization": "0.928571", "Cycles": "159744", "Energy [uJ]": "77.9517", "EDP [J*cycle]": "1.245231e+01", "Area [mm^2]": "1.928614", "LastLevelAccesses": "43648", "MAC energy [pJ]": "2.200350", "Computes": "24920064", "Algorithmic computes": "24920064", "Runtime [s]": "26.86"}, "mobilenet_tinyimagenet_025_layer26": {"Workload": "mobilenet_tinyimagenet_025_layer26", "Optimized_metric_1": "energy", "Optimized_metric_2": "delay", "pJ/Compute": "3.45299", "Utilization": "0.428571", "Cycles": "294912", "Energy [uJ]": "73.3197", "EDP [J*cycle]": "2.162287e+01", "Area [mm^2]": "1.928614", "LastLevelAccesses": "86528", "MAC energy [pJ]": "2.200350", "Computes": "21233664", "Algorithmic computes": "21233664", "Runtime [s]": "33.48"}, "mobilenet_tinyimagenet_025_layer12": {"Workload": "mobilenet_tinyimagenet_025_layer12", "Optimized_metric_1": "energy", "Optimized_metric_2": "delay", "pJ/Compute": "3.69372", "Utilization": "0.928571", "Cycles": "39936", "Energy [uJ]": "23.0119", "EDP [J*cycle]": "9.190049e-01", "Area [mm^2]": "1.928614", "LastLevelAccesses": "33344", "MAC energy [pJ]": "2.200350", "Computes": "6230016", "Algorithmic computes": "6230016", "Runtime [s]": "23.45"}, "mobilenet_tinyimagenet_025_layer28": {"Workload": "mobilenet_tinyimagenet_025_layer28", "Optimized_metric_1": "energy", "Optimized_metric_2": "delay", "pJ/Compute": "4.73496", "Utilization": "0.571429", "Cycles": "9600", "Energy [uJ]": "4.36374", "EDP [J*cycle]": "4.189190e-02", "Area [mm^2]": "1.928614", "LastLevelAccesses": "9608", "MAC energy [pJ]": "2.200350", "Computes": "921600", "Algorithmic computes": "921600", "Runtime [s]": "22.09"}}